setup.cfg
setup.py
google_spreadsheet/__init__.py
google_spreadsheet/api.py
python_google_spreadsheet.egg-info/PKG-INFO
python_google_spreadsheet.egg-info/SOURCES.txt
python_google_spreadsheet.egg-info/dependency_links.txt
python_google_spreadsheet.egg-info/requires.txt
python_google_spreadsheet.egg-info/top_level.txt
python_google_spreadsheet.egg-info/zip-safe