Metadata-Version: 1.1
Name: python-google-spreadsheet
Version: 1.0.4
Summary: A simple Python wrapper for the Google Spreadsheets API
Home-page: https://github.com/yoavaviram/python-google-spreadsheet
Author: Yoav Aviram
Author-email: support@cleverblocks.com
License: BSD
Keywords: google,docs,spreadsheets,api
Platform: UNKNOWN
Classifier: Development Status :: 5 - Production/Stable
Classifier: Environment :: Console
Classifier: Intended Audience :: Developers
Classifier: Natural Language :: English
Classifier: Operating System :: OS Independent
Classifier: Programming Language :: Python
Classifier: Topic :: Software Development :: Libraries :: Python Modules
Classifier: Topic :: Internet :: WWW/HTTP :: Dynamic Content :: CGI Tools/Libraries
Classifier: Topic :: Utilities
Classifier: License :: OSI Approved :: BSD License
